designs/src/ihp-chip-spi/spi_controller.v
module spi_controller(
  input clk,
  input rst,
  input spi_done,
  input [7:0] spi_dout,
  output reg [7:0] din,
  output reg [7:0] win,
  output reg [7:0] bias
);

  reg [1:0] cS, nS;
  parameter IDLE = 2'b00;
  parameter DIN = 2'b01;
  parameter WIN = 2'b10;
  parameter BIAS = 2'b11;
  reg din_en, win_en, bias_en;

  //state register
  always @(posedge clk, posedge rst) begin
    if(rst) begin
      cS <= IDLE;
      din <= 0;
      win <= 0;
      bias <= 0;
    end else begin 
      cS <= nS;
      case(cS)
        IDLE: din_en <= 1'b1;
        DIN: if(din_en) begin 
               din <= spi_dout;
               din_en <= 1'b0;
               win_en <= 1'b1;
        end 
        WIN: if(win_en) begin
               win <= spi_dout;
               win_en <= 1'b0;
               bias_en <= 1'b1;
        end
        BIAS: if(bias_en) begin
                bias <= spi_dout;
                bias_en <= 1'b0;
                din_en <= 1'b1;
        end
      endcase
    end
  end 

  //next state logic
  always @(*) begin 
    case(cS)
      IDLE: if(spi_done) nS = DIN;
      DIN:  begin
              if(spi_done) nS = WIN;
              //din <= spi_dout;
            end
      WIN:  begin
              if(spi_done) nS = BIAS;
              //win <= spi_dout;
            end
      BIAS: begin
              if(spi_done) nS = DIN;
              //else         nS = IDLE;
              //bias <= spi_dout;
            end
      default: nS = IDLE;
    endcase
  end 


endmodule

designs/src/ihp-chip-spi/spi_controller_tb.v
module spi_controller_tb();

  reg clk;
  reg rst;
  reg spi_done;
  reg [7:0] spi_dout;
  wire [7:0] din;
  wire [7:0] win;
  wire [7:0] bias;

  spi_controller dut(.clk(clk),
                     .rst(rst),
                     .spi_done(spi_done),
                     .spi_dout(spi_dout),
                     .din(din),
                     .win(win),
                     .bias(bias)
  );

initial begin

  $dumpfile("spi_controller.vcd");
  $dumpvars();

  clk=0;
  rst=0;
  spi_done=0;
  #10; spi_done=1; spi_dout=127; #5; spi_done=0;
  #49; spi_done=1; spi_dout=12; #5; spi_done=0;
  #49; spi_done=1; spi_dout=1; #5; spi_done=0;
  #49; spi_done=1; spi_dout=16; #5; spi_done=0;
  #20;


  #10 $finish;

end

always #3 clk = ~clk;

endmodule

designs/src/ihp-chip-spi/spi_controller.vcd
$date
	Wed Oct  9 15:26:24 2024
$end
$version
	Icarus Verilog
$end
$timescale
	1s
$end
$scope module spi_controller_tb $end
$var wire 8 ! win [7:0] $end
$var wire 8 " din [7:0] $end
$var wire 8 # bias [7:0] $end
$var reg 1 $ clk $end
$var reg 1 % rst $end
$var reg 1 & spi_done $end
$var reg 8 ' spi_dout [7:0] $end
$scope module dut $end
$var wire 1 $ clk $end
$var wire 1 % rst $end
$var wire 1 & spi_done $end
$var wire 8 ( spi_dout [7:0] $end
$var parameter 2 ) BIAS $end
$var parameter 2 * DIN $end
$var parameter 2 + IDLE $end
$var parameter 2 , WIN $end
$var reg 8 - bias [7:0] $end
$var reg 1 . bias_en $end
$var reg 2 / cS [1:0] $end
$var reg 8 0 din [7:0] $end
$var reg 1 1 din_en $end
$var reg 2 2 nS [1:0] $end
$var reg 8 3 win [7:0] $end
$var reg 1 4 win_en $end
$upscope $end
$upscope $end
$enddefinitions $end
$comment Show the parameter values. $end
$dumpall
b10 ,
b0 +
b1 *
b11 )
$end
#0
$dumpvars
x4
bx 3
b0 2
x1
bx 0
bx /
x.
bx -
bx (
bx '
0&
0%
0$
bx #
bx "
bx !
$end
#3
b0 /
1$
#6
0$
#9
11
1$
#10
b1 2
b1111111 '
b1111111 (
1&
#12
0$
#15
b1 /
1$
0&
#18
0$
#21
14
01
b1111111 "
b1111111 0
1$
#24
0$
#27
1$
#30
0$
#33
1$
#36
0$
#39
1$
#42
0$
#45
1$
#48
0$
#51
1$
#54
0$
#57
1$
#60
0$
#63
1$
#64
b10 2
b1100 '
b1100 (
1&
#66
0$
#69
b10 /
1$
0&
#72
0$
#75
1.
04
b1100 !
b1100 3
1$
#78
0$
#81
1$
#84
0$
#87
1$
#90
0$
#93
1$
#96
0$
#99
1$
#102
0$
#105
1$
#108
0$
#111
1$
#114
0$
#117
1$
#118
b11 2
b1 '
b1 (
1&
#120
0$
#123
b11 /
1$
0&
#126
0$
#129
11
0.
b1 #
b1 -
1$
#132
0$
#135
1$
#138
0$
#141
1$
#144
0$
#147
1$
#150
0$
#153
1$
#156
0$
#159
1$
#162
0$
#165
1$
#168
0$
#171
1$
#172
b1 2
b10000 '
b10000 (
1&
#174
0$
#177
b1 /
1$
0&
#180
0$
#183
14
01
b10000 "
b10000 0
1$
